src/__init__.py
src/knowage-python.py
src/app/__init__.py
src/app/services/__init__.py
src/app/services/catalog_resource.py
src/app/services/dataset_resource.py
src/app/services/widget_resource.py
src/app/utilities/__init__.py
src/app/utilities/configs.py
src/app/utilities/security.py
src/app/utilities/utils.py
src/logs/__init__.py
knowage_python-8.0.2.dist-info/LICENSE
knowage_python-8.0.2.dist-info/METADATA
knowage_python-8.0.2.dist-info/WHEEL
knowage_python-8.0.2.dist-info/top_level.txt
knowage_python-8.0.2.dist-info/RECORD
